{"coords": {"time": {"dims": ["time"], "attrs": {"standard_name": "time", "axis": "T", "time_zone": "UTC"}, "data": ["2020-10-26T15:00:00", "2020-10-26T16:00:00", "2020-10-26T17:00:00", "2020-10-26T18:00:00", "2020-10-26T19:00:00", "2020-10-26T20:00:00", "2020-10-26T21:00:00", "2020-10-26T22:00:00", "2020-10-26T23:00:00", "2020-10-27T00:00:00", "2020-10-27T01:00:00", "2020-10-27T02:00:00", "2020-10-27T03:00:00", "2020-10-27T04:00:00", "2020-10-27T05:00:00", "2020-10-27T06:00:00", "2020-10-27T07:00:00", "2020-10-27T08:00:00", "2020-10-27T09:00:00", "2020-10-27T10:00:00", "2020-10-27T11:00:00", "2020-10-27T12:00:00", "2020-10-27T13:00:00", "2020-10-27T14:00:00", "2020-10-27T15:00:00", "2020-10-27T16:00:00", "2020-10-27T17:00:00", "2020-10-27T18:00:00", "2020-10-27T19:00:00", "2020-10-27T20:00:00", "2020-10-27T21:00:00"]}, "lon": {"dims": [], "attrs": {"standard_name": "longitude", "long_name": "longitude", "units": "degrees_east", "axis": "X"}, "data": 13.375}, "lat": {"dims": [], "attrs": {"standard_name": "latitude", "long_name": "latitude", "units": "degrees_north", "axis": "Y"}, "data": 52.5}, "Name": {"dims": [], "attrs": {}, "data": "Berlin"}, "Id": {"dims": [], "attrs": {}, "data": 2}}, "attrs": {}, "dims": {"time": 31}, "data_vars": {"downward_direct": {"dims": ["time"], "attrs": {"long_name": "Downward direct short wave radiation flux at surface (mean over hour time time-stamp)", "units": "W m-2", "param": "198.4.0", "institution": "DWD"}, "data": [0.0, 0.02, 0.0, 0.01, 0.0, 0.0, 0.0, 0.0, 0.0, 0.0, 0.0, 0.0, 0.0, 0.0, 0.0, 0.0, 0.03, 11.59, 38.44, 33.73, 47.93, 5.93, 4.15, 55.05, 40.25, 3.04, 0.0, 0.06, 0.04, 0.0, 0.0]}, "downward_diffuse": {"dims": ["time"], "attrs": {"long_name": "Downward diffusive short wave radiation flux at surface (mean over hour time time-stamp)", "units": "W m-2", "param": "199.4.0", "institution": "DWD"}, "data": [0.0, 1.66, 0.0, 0.0, 0.0, 0.0, 0.0, 0.0, 0.0, 0.0, 0.0, 0.0, 0.0, 0.0, 0.0, 0.0, 25.8, 87.99, 145.84, 191.12, 215.71, 192.64, 145.87, 110.13, 57.27, 11.28, 0.0, 0.0, 0.0, 0.0, 0.0]}, "relative_humidity": {"dims": ["time"], "attrs": {"standard_name": "relative_humidity", "long_name": "2 metre relative humidity", "units": "%", "param": "1.1.0", "institution": "DWD"}, "data": [81.84, 87.37, 91.01, 92.03, 93.63, 91.89, 93.05, 92.21, 89.41, 86.23, 85.04, 86.68, 88.55, 88.55, 88.58, 87.92, 86.03, 81.05, 76.4, 73.04, 69.14, 65.27, 65.87, 64.8, 66.83, 73.12, 76.58, 78.08, 77.05, 77.64, 79.13]}, "air_temperature": {"dims": ["time"], "attrs": {"standard_name": "air_temperature", "long_name": "2 metre temperature", "units": "C", "param": "0.0.0", "institution": "DWD"}, "data": [12.94, 12.48, 11.72, 11.2, 10.92, 10.67, 10.46, 10.36, 10.1, 9.71, 9.09, 8.65, 8.22, 7.89, 7.63, 7.54, 7.88, 8.92, 10.14, 11.14, 11.98, 12.27, 12.28, 12.65, 12.36, 11.23, 10.27, 9.69, 9.4, 9.07, 8.76]}, "eastward_wind": {"dims": ["time"], "attrs": {"standard_name": "eastward_wind", "long_name": "10 metre U wind component", "units": "m s**-1", "param": "2.2.0", "institution": "DWD"}, "data": [1.24, 1.7, 2.48, 1.87, 2.24, 1.78, 1.46, 1.39, 1.49, 1.78, 1.23, 0.81, 0.4, 0.58, 0.52, 0.65, 0.33, 0.75, 0.99, 1.51, 1.87, 2.97, 2.47, 1.44, 0.99, 0.24, 0.21, 0.59, 0.73, 0.69, 0.84]}, "northward_wind": {"dims": ["time"], "attrs": {"standard_name": "northward_wind", "long_name": "10 metre V wind component", "units": "m s**-1", "param": "3.2.0", "institution": "DWD"}, "data": [-0.08, -0.29, -0.11, 0.28, 1.02, 1.41, 1.35, 1.59, 1.57, 1.5, 1.54, 2.04, 2.19, 2.28, 2.29, 2.21, 2.44, 2.88, 2.94, 2.98, 3.23, 3.42, 3.41, 3.26, 3.12, 2.47, 2.5, 2.61, 3.03, 3.11, 3.3]}, "PET": {"dims": ["time"], "attrs": {"standard_name": "PET", "long_name": "physiological equivalent temperature", "units": "C"}, "data": ["null", 8.38, 6.39, 6.21, 5.54, 5.39, 5.35, 5.15, 4.82, 4.21, 3.77, 3.15, 2.68, 2.25, 1.97, 1.89, 2.68, 5.01, 7.82, 9.14, 10.43, 8.94, 8.51, 10.75, 10.09, 7.45, 4.52, 3.82, 3.31, 2.92, 2.5]}, "UTCI": {"dims": ["time"], "attrs": {"standard_name": "UTCI", "long_name": "Universal Thermal Climate Index", "units": "C"}, "data": ["null", 10.96, 7.48, 8.37, 6.63, 6.8, 7.29, 6.85, 6.31, 5.24, 5.42, 4.34, 3.81, 3.05, 2.75, 2.74, 3.43, 5.42, 8.65, 9.69, 10.52, 7.09, 6.92, 10.89, 10.57, 8.7, 4.92, 3.82, 2.25, 1.63, 0.66]}, "Tmrt": {"dims": ["time"], "attrs": {"standard_name": "Tmrt", "long_name": "Mean Radiant Temperature", "units": "C"}, "data": ["null", 10.45, 7.24, 6.71, 6.43, 6.17, 5.96, 5.86, 5.58, 4.88, 4.23, 3.79, 3.37, 3.04, 2.77, 2.67, 5.21, 12.72, 20.35, 23.02, 26.61, 21.6, 18.81, 25.07, 22.54, 13.38, 4.8, 4.21, 3.91, 3.57, 3.26]}, "IO": {"dims": ["time"], "attrs": {"standard_name": "IO", "long_name": "Clear-sky solar radiation", "units": "W/m/m"}, "data": ["null", 38.84, 0.0, 0.0, 0.0, 0.0, 0.0, 0.0, 0.0, 0.0, 0.0, 0.0, 0.0, 0.0, 0.0, 0.0, 83.81, 225.16, 339.6, 417.85, 454.65, 447.74, 396.42, 304.97, 180.0, 34.12, 0.0, 0.0, 0.0, 0.0, 0.0]}, "altitude": {"dims": ["time"], "attrs": {"standard_name": "altitude", "long_name": "Solar altitude", "units": "deg"}, "data": ["null", 1.97, -7.11, -16.17, -25.22, -33.84, -41.44, -47.2, -50.14, -49.58, -45.66, -39.23, -31.24, -22.44, -13.37, -4.22, 4.32, 11.77, 17.94, 22.29, 24.38, 23.96, 21.07, 16.06, 9.39, 1.7, -7.39, -16.44, -25.5, -34.13, -41.75]}, "azimuth": {"dims": ["time"], "attrs": {"standard_name": "azimuth", "long_name": "Solar azimuth", "units": "deg"}, "data": ["null", 246.4, 258.19, 269.91, 282.19, 295.79, 311.61, 330.47, 352.24, 14.99, 35.96, 53.81, 68.84, 81.94, 93.98, 105.68, 117.6, 130.25, 143.95, 158.81, 174.56, 190.58, 206.09, 220.57, 233.88, 246.22, 258.0, 269.71, 281.98, 295.58, 311.43]}}}
