{"coords": {"time": {"dims": ["time"], "attrs": {"standard_name": "time", "axis": "T", "time_zone": "UTC"}, "data": ["2020-07-07T21:00:00", "2020-07-07T22:00:00", "2020-07-07T23:00:00", "2020-07-08T00:00:00", "2020-07-08T01:00:00", "2020-07-08T02:00:00", "2020-07-08T03:00:00", "2020-07-08T04:00:00", "2020-07-08T05:00:00", "2020-07-08T06:00:00", "2020-07-08T07:00:00", "2020-07-08T08:00:00", "2020-07-08T09:00:00", "2020-07-08T10:00:00", "2020-07-08T11:00:00", "2020-07-08T12:00:00", "2020-07-08T13:00:00", "2020-07-08T14:00:00", "2020-07-08T15:00:00", "2020-07-08T16:00:00", "2020-07-08T17:00:00", "2020-07-08T18:00:00", "2020-07-08T19:00:00", "2020-07-08T20:00:00", "2020-07-08T21:00:00", "2020-07-08T22:00:00", "2020-07-08T23:00:00", "2020-07-09T00:00:00", "2020-07-09T01:00:00", "2020-07-09T02:00:00", "2020-07-09T03:00:00"]}, "lon": {"dims": [], "attrs": {"standard_name": "longitude", "long_name": "longitude", "units": "degrees_east", "axis": "X"}, "data": 12.0}, "lat": {"dims": [], "attrs": {"standard_name": "latitude", "long_name": "latitude", "units": "degrees_north", "axis": "Y"}, "data": 57.6875}, "Name": {"dims": [], "attrs": {}, "data": "Gothenburg"}, "Id": {"dims": [], "attrs": {}, "data": 71415}}, "attrs": {}, "dims": {"time": 31}, "data_vars": {"downward_direct": {"dims": ["time"], "attrs": {"long_name": "Downward direct short wave radiation flux at surface (mean over hour time time-stamp)", "units": "W m-2", "param": "198.4.0", "institution": "DWD"}, "data": [0.0, 0.0, 0.0, 0.0, 0.0, 0.0, 0.25, 9.13, 59.46, 163.19, 238.28, 367.75, 477.63, 520.68, 206.79, 51.03, 156.63, 310.94, 358.14, 335.18, 251.31, 160.26, 64.11, 8.6, 0.02, 0.0, 0.1, 0.0, 0.0, 0.09, 0.38]}, "downward_diffuse": {"dims": ["time"], "attrs": {"long_name": "Downward diffusive short wave radiation flux at surface (mean over hour time time-stamp)", "units": "W m-2", "param": "199.4.0", "institution": "DWD"}, "data": [0.0, 0.0, 0.0, 0.0, 0.0, 0.0, 2.57, 29.52, 71.01, 103.73, 141.13, 163.4, 178.91, 194.5, 318.67, 449.64, 420.74, 276.46, 195.32, 143.01, 107.98, 71.4, 45.86, 15.94, 0.0, 0.0, 0.0, 0.0, 0.0, 0.0, 2.88]}, "relative_humidity": {"dims": ["time"], "attrs": {"standard_name": "relative_humidity", "long_name": "2 metre relative humidity", "units": "%", "param": "1.1.0", "institution": "DWD"}, "data": [83.36, 84.62, 85.18, 85.77, 86.33, 88.15, 89.08, 88.23, 81.94, 74.41, 69.92, 60.47, 55.64, 51.65, 63.71, 69.44, 67.99, 67.14, 63.03, 60.52, 61.02, 60.94, 67.21, 72.88, 77.71, 88.32, 89.95, 93.6, 94.31, 94.84, 95.33]}, "air_temperature": {"dims": ["time"], "attrs": {"standard_name": "air_temperature", "long_name": "2 metre temperature", "units": "C", "param": "0.0.0", "institution": "DWD"}, "data": [10.7, 10.61, 10.63, 10.73, 10.77, 10.78, 10.81, 11.05, 11.9, 12.74, 13.41, 14.44, 15.08, 15.69, 14.62, 14.27, 14.55, 14.78, 15.15, 15.44, 15.22, 14.71, 13.97, 13.14, 12.47, 12.11, 12.15, 12.19, 12.31, 12.12, 11.86]}, "eastward_wind": {"dims": ["time"], "attrs": {"standard_name": "eastward_wind", "long_name": "10 metre U wind component", "units": "m s**-1", "param": "2.2.0", "institution": "DWD"}, "data": [4.99, 4.56, 4.18, 3.79, 3.58, 3.22, 2.97, 2.44, 2.66, 3.13, 3.52, 3.0, 2.4, 2.59, 3.95, 2.89, 2.83, 2.69, 2.77, 2.91, 2.98, 2.6, 2.17, 1.04, 0.36, 0.93, 0.58, 0.14, -0.16, -0.53, -0.43]}, "northward_wind": {"dims": ["time"], "attrs": {"standard_name": "northward_wind", "long_name": "10 metre V wind component", "units": "m s**-1", "param": "3.2.0", "institution": "DWD"}, "data": [0.81, 0.52, 0.39, 0.37, 0.33, 0.29, -0.17, -0.34, -0.62, -1.86, -2.06, -2.93, -3.05, -1.78, -0.66, -0.62, -0.26, -0.32, -0.2, -0.06, 0.1, 0.47, 0.81, 0.76, 1.08, 1.32, 1.42, 1.38, 1.38, 1.33, 1.17]}, "PET": {"dims": ["time"], "attrs": {"standard_name": "PET", "long_name": "physiological equivalent temperature", "units": "C"}, "data": ["null", 4.17, 4.3, 4.61, 4.72, 4.89, 5.15, 7.11, 10.12, 12.94, 14.54, 17.53, 20.02, 22.78, 17.03, 18.09, 19.94, 21.1, 21.96, 21.69, 20.0, 18.52, 15.76, 12.77, 7.98, 7.23, 7.35, 7.55, 7.69, 7.45, 7.57]}, "UTCI": {"dims": ["time"], "attrs": {"standard_name": "UTCI", "long_name": "Universal Thermal Climate Index", "units": "C"}, "data": ["null", 0.36, 1.31, 2.54, 3.13, 4.12, 5.04, 8.68, 11.87, 13.83, 15.01, 17.85, 20.46, 23.01, 17.54, 19.77, 21.52, 22.51, 22.95, 22.61, 21.25, 20.14, 17.92, 15.64, 10.79, 9.75, 10.03, 10.5, 10.65, 10.38, 10.74]}, "Tmrt": {"dims": ["time"], "attrs": {"standard_name": "Tmrt", "long_name": "Mean Radiant Temperature", "units": "C"}, "data": ["null", 5.23, 5.25, 5.72, 5.77, 5.8, 6.33, 12.33, 21.98, 33.28, 38.73, 46.75, 51.86, 53.74, 43.64, 43.25, 47.51, 49.35, 50.91, 50.45, 46.89, 41.96, 33.58, 20.97, 7.29, 7.03, 7.08, 7.15, 7.29, 7.1, 7.52]}, "IO": {"dims": ["time"], "attrs": {"standard_name": "IO", "long_name": "Clear-sky solar radiation", "units": "W/m/m"}, "data": ["null", 0.0, 0.0, 0.0, 0.0, 0.0, 3.44, 109.66, 237.9, 375.0, 510.37, 635.98, 741.58, 820.32, 862.27, 870.73, 845.19, 785.37, 696.45, 582.98, 452.93, 315.92, 180.64, 59.37, 0.0, 0.0, 0.0, 0.0, 0.0, 0.0, 1.2]}, "altitude": {"dims": ["time"], "attrs": {"standard_name": "altitude", "long_name": "Solar altitude", "units": "deg"}, "data": ["null", -6.87, -9.34, -9.91, -8.52, -5.21, 0.16, 5.87, 12.86, 20.53, 28.5, 36.38, 43.69, 49.76, 53.69, 54.63, 52.32, 47.35, 40.64, 33.01, 25.03, 17.14, 9.7, 3.13, -2.1, -6.98, -9.46, -10.02, -8.64, -5.35, 0.05]}, "azimuth": {"dims": ["time"], "attrs": {"standard_name": "azimuth", "long_name": "Solar azimuth", "units": "deg"}, "data": ["null", 335.22, 348.99, 3.03, 16.99, 30.57, 43.58, 56.04, 68.12, 80.17, 92.64, 106.17, 121.59, 139.85, 161.4, 185.13, 208.2, 228.35, 245.28, 259.77, 272.75, 284.97, 296.99, 309.2, 321.88, 335.15, 348.94, 3.0, 16.98, 30.57, 43.59]}}}
