{"coords": {"time": {"dims": ["time"], "attrs": {"standard_name": "time", "axis": "T", "time_zone": "UTC"}, "data": ["2020-08-06T09:00:00", "2020-08-06T10:00:00", "2020-08-06T11:00:00", "2020-08-06T12:00:00", "2020-08-06T13:00:00", "2020-08-06T14:00:00", "2020-08-06T15:00:00", "2020-08-06T16:00:00", "2020-08-06T17:00:00", "2020-08-06T18:00:00", "2020-08-06T19:00:00", "2020-08-06T20:00:00", "2020-08-06T21:00:00", "2020-08-06T22:00:00", "2020-08-06T23:00:00", "2020-08-07T00:00:00", "2020-08-07T01:00:00", "2020-08-07T02:00:00", "2020-08-07T03:00:00", "2020-08-07T04:00:00", "2020-08-07T05:00:00", "2020-08-07T06:00:00", "2020-08-07T07:00:00", "2020-08-07T08:00:00", "2020-08-07T09:00:00", "2020-08-07T10:00:00", "2020-08-07T11:00:00", "2020-08-07T12:00:00", "2020-08-07T13:00:00", "2020-08-07T14:00:00", "2020-08-07T15:00:00"]}, "lon": {"dims": [], "attrs": {"standard_name": "longitude", "long_name": "longitude", "units": "degrees_east", "axis": "X"}, "data": 18.125}, "lat": {"dims": [], "attrs": {"standard_name": "latitude", "long_name": "latitude", "units": "degrees_north", "axis": "Y"}, "data": 56.9375}, "Name": {"dims": [], "attrs": {}, "data": "Hoburg"}, "Id": {"dims": [], "attrs": {}, "data": 68545}}, "attrs": {}, "dims": {"time": 31}, "data_vars": {"downward_direct": {"dims": ["time"], "attrs": {"long_name": "Downward direct short wave radiation flux at surface (mean over hour time time-stamp)", "units": "W m-2", "param": "198.4.0", "institution": "DWD"}, "data": [0.0, 451.33, 558.23, 560.38, 522.56, 448.44, 345.53, 230.17, 119.23, 34.78, 1.72, 0.0, 0.0, 0.1, 0.0, 0.06, 0.0, 0.0, 0.11, 3.97, 43.54, 130.73, 237.91, 343.05, 371.41, 311.01, 144.8, 130.24, 246.54, 336.03, 301.32]}, "downward_diffuse": {"dims": ["time"], "attrs": {"long_name": "Downward diffusive short wave radiation flux at surface (mean over hour time time-stamp)", "units": "W m-2", "param": "199.4.0", "institution": "DWD"}, "data": [0.0, 178.76, 142.49, 141.5, 134.16, 124.54, 114.07, 98.71, 77.2, 46.94, 9.45, 0.0, 0.0, 0.0, 0.0, 0.0, 0.0, 0.0, 0.0, 16.85, 58.58, 89.31, 111.88, 130.34, 183.04, 258.73, 341.81, 351.58, 283.8, 185.42, 134.69]}, "relative_humidity": {"dims": ["time"], "attrs": {"standard_name": "relative_humidity", "long_name": "2 metre relative humidity", "units": "%", "param": "1.1.0", "institution": "DWD"}, "data": [74.96, 74.53, 73.55, 72.37, 71.78, 71.75, 71.59, 71.92, 72.61, 73.97, 75.08, 75.34, 76.06, 77.0, 78.04, 77.64, 77.72, 76.72, 76.9, 77.7, 77.69, 76.61, 72.87, 71.29, 70.73, 70.59, 70.61, 71.02, 70.99, 70.65, 71.91]}, "air_temperature": {"dims": ["time"], "attrs": {"standard_name": "air_temperature", "long_name": "2 metre temperature", "units": "C", "param": "0.0.0", "institution": "DWD"}, "data": [19.63, 19.77, 19.86, 19.89, 19.85, 19.75, 19.64, 19.42, 19.2, 18.94, 18.74, 18.68, 18.6, 18.51, 18.38, 18.29, 18.22, 18.18, 18.08, 18.07, 18.36, 18.89, 19.42, 19.78, 20.05, 20.15, 20.13, 20.19, 20.4, 20.49, 20.26]}, "eastward_wind": {"dims": ["time"], "attrs": {"standard_name": "eastward_wind", "long_name": "10 metre U wind component", "units": "m s**-1", "param": "2.2.0", "institution": "DWD"}, "data": [3.51, 3.63, 3.65, 3.57, 3.45, 3.05, 2.54, 2.47, 2.47, 2.36, 2.07, 1.92, 1.84, 1.63, 1.36, 0.83, 0.48, 0.4, 0.31, -0.04, -0.45, -0.87, -1.02, -1.23, -1.27, -1.05, -1.42, -1.58, -1.68, -2.29, -2.47]}, "northward_wind": {"dims": ["time"], "attrs": {"standard_name": "northward_wind", "long_name": "10 metre V wind component", "units": "m s**-1", "param": "3.2.0", "institution": "DWD"}, "data": [4.46, 4.86, 5.55, 6.18, 5.84, 5.28, 5.34, 5.42, 5.31, 5.1, 4.86, 4.44, 3.59, 2.94, 2.72, 2.86, 2.89, 2.49, 2.01, 1.82, 1.81, 2.06, 2.52, 2.55, 2.76, 2.75, 2.69, 2.24, 1.81, 1.89, 1.96]}, "PET": {"dims": ["time"], "attrs": {"standard_name": "PET", "long_name": "physiological equivalent temperature", "units": "C"}, "data": ["null", 22.81, 23.01, 22.87, 23.2, 23.42, 22.47, 20.67, 18.86, 16.44, 14.6, 12.93, 13.05, 13.18, 13.17, 13.13, 13.07, 13.21, 13.36, 14.77, 17.4, 20.16, 22.77, 25.27, 26.38, 26.61, 24.55, 25.22, 27.64, 27.96, 26.75]}, "UTCI": {"dims": ["time"], "attrs": {"standard_name": "UTCI", "long_name": "Universal Thermal Climate Index", "units": "C"}, "data": ["null", 22.16, 22.19, 22.0, 22.25, 22.52, 21.83, 20.28, 18.23, 15.36, 13.15, 11.15, 12.33, 13.45, 13.93, 13.97, 13.96, 14.64, 15.42, 17.23, 19.91, 22.31, 23.87, 25.48, 26.1, 26.31, 24.88, 25.52, 27.26, 27.19, 26.33]}, "Tmrt": {"dims": ["time"], "attrs": {"standard_name": "Tmrt", "long_name": "Mean Radiant Temperature", "units": "C"}, "data": ["null", 53.26, 55.39, 56.36, 56.42, 55.21, 52.42, 47.75, 40.84, 30.66, 22.24, 13.63, 13.54, 13.47, 13.35, 13.44, 13.37, 13.31, 13.21, 17.52, 25.4, 34.25, 41.9, 47.55, 50.55, 50.42, 45.91, 46.05, 49.99, 52.84, 51.34]}, "IO": {"dims": ["time"], "attrs": {"standard_name": "IO", "long_name": "Clear-sky solar radiation", "units": "W/m/m"}, "data": ["null", 766.91, 800.21, 796.35, 755.24, 679.63, 574.9, 448.1, 307.93, 164.46, 31.32, 0.0, 0.0, 0.0, 0.0, 0.0, 0.0, 0.0, 0.0, 57.39, 194.26, 337.37, 475.42, 597.96, 696.54, 764.68, 797.77, 793.06, 751.11, 675.21, 570.08]}, "altitude": {"dims": ["time"], "attrs": {"standard_name": "altitude", "long_name": "Solar altitude", "units": "deg"}, "data": ["null", 46.66, 49.34, 48.98, 45.66, 40.05, 32.96, 25.08, 16.93, 8.93, 1.62, -5.41, -10.91, -14.71, -16.59, -16.37, -14.06, -9.88, -3.9, 3.06, 10.58, 18.63, 26.74, 34.47, 41.26, 46.4, 49.06, 48.7, 45.39, 39.79, 32.71]}, "azimuth": {"dims": ["time"], "attrs": {"standard_name": "azimuth", "long_name": "Solar azimuth", "units": "deg"}, "data": ["null", 150.21, 171.4, 193.45, 214.16, 232.28, 247.89, 261.66, 274.36, 286.61, 298.91, 311.67, 325.13, 339.36, 354.17, 9.18, 23.9, 37.97, 51.28, 63.93, 76.2, 88.52, 101.41, 115.55, 131.67, 150.37, 171.48, 193.44, 214.08, 232.15, 247.74]}}}
