{"coords": {"time": {"dims": ["time"], "attrs": {"standard_name": "time", "axis": "T", "time_zone": "UTC"}, "data": ["2020-08-24T15:00:00", "2020-08-24T16:00:00", "2020-08-24T17:00:00", "2020-08-24T18:00:00", "2020-08-24T19:00:00", "2020-08-24T20:00:00", "2020-08-24T21:00:00", "2020-08-24T22:00:00", "2020-08-24T23:00:00", "2020-08-25T00:00:00", "2020-08-25T01:00:00", "2020-08-25T02:00:00", "2020-08-25T03:00:00", "2020-08-25T04:00:00", "2020-08-25T05:00:00", "2020-08-25T06:00:00", "2020-08-25T07:00:00", "2020-08-25T08:00:00", "2020-08-25T09:00:00", "2020-08-25T10:00:00", "2020-08-25T11:00:00", "2020-08-25T12:00:00", "2020-08-25T13:00:00", "2020-08-25T14:00:00", "2020-08-25T15:00:00", "2020-08-25T16:00:00", "2020-08-25T17:00:00", "2020-08-25T18:00:00", "2020-08-25T19:00:00", "2020-08-25T20:00:00", "2020-08-25T21:00:00"]}, "lon": {"dims": [], "attrs": {"standard_name": "longitude", "long_name": "longitude", "units": "degrees_east", "axis": "X"}, "data": -0.1875}, "lat": {"dims": [], "attrs": {"standard_name": "latitude", "long_name": "latitude", "units": "degrees_north", "axis": "Y"}, "data": 51.5}, "Name": {"dims": [], "attrs": {}, "data": "London"}, "Id": {"dims": [], "attrs": {}, "data": 1}}, "attrs": {}, "dims": {"time": 31}, "data_vars": {"downward_direct": {"dims": ["time"], "attrs": {"long_name": "Downward direct short wave radiation flux at surface (mean over hour time time-stamp)", "units": "W m-2", "param": "198.4.0", "institution": "DWD"}, "data": [0.0, 115.94, 50.72, 26.0, 5.97, 0.01, 0.02, 0.0, 0.0, 0.01, 0.0, 0.01, 0.01, 0.0, 0.0, 0.39, 1.36, 0.7, 1.35, 14.44, 61.57, 189.3, 389.91, 271.5, 137.78, 64.7, 84.55, 57.21, 6.88, 0.08, 0.0]}, "downward_diffuse": {"dims": ["time"], "attrs": {"long_name": "Downward diffusive short wave radiation flux at surface (mean over hour time time-stamp)", "units": "W m-2", "param": "199.4.0", "institution": "DWD"}, "data": [0.0, 186.41, 144.35, 72.5, 24.48, 0.0, 0.0, 0.0, 0.0, 0.0, 0.0, 0.0, 0.0, 0.0, 0.0, 4.12, 10.91, 15.69, 18.7, 61.39, 121.02, 219.26, 233.1, 234.58, 219.25, 165.14, 133.85, 70.96, 19.63, 0.0, 0.0]}, "relative_humidity": {"dims": ["time"], "attrs": {"standard_name": "relative_humidity", "long_name": "2 metre relative humidity", "units": "%", "param": "1.1.0", "institution": "DWD"}, "data": [54.42, 62.28, 78.02, 82.71, 83.21, 87.26, 88.48, 91.05, 92.13, 91.9, 94.42, 95.25, 93.81, 92.79, 90.71, 88.81, 89.03, 89.99, 87.15, 84.25, 80.15, 71.88, 61.61, 64.34, 67.8, 69.33, 70.31, 72.81, 73.08, 74.95, 73.32]}, "air_temperature": {"dims": ["time"], "attrs": {"standard_name": "air_temperature", "long_name": "2 metre temperature", "units": "C", "param": "0.0.0", "institution": "DWD"}, "data": [20.52, 19.93, 18.75, 17.88, 17.37, 16.69, 16.29, 15.92, 15.89, 15.79, 15.62, 15.57, 15.66, 15.72, 15.63, 15.51, 15.45, 15.72, 16.09, 16.85, 18.4, 20.52, 21.58, 20.72, 20.2, 19.86, 19.68, 18.87, 18.26, 17.61, 17.2]}, "eastward_wind": {"dims": ["time"], "attrs": {"standard_name": "eastward_wind", "long_name": "10 metre U wind component", "units": "m s**-1", "param": "2.2.0", "institution": "DWD"}, "data": [2.52, 2.71, 2.1, 1.81, 1.08, 0.71, 0.76, 0.58, 0.46, 0.57, 0.18, 0.28, 0.21, 0.21, -0.02, -0.49, -0.91, 0.49, 0.04, 1.79, 1.63, 4.6, 5.59, 5.89, 5.7, 5.66, 5.44, 5.8, 5.96, 6.14, 6.58]}, "northward_wind": {"dims": ["time"], "attrs": {"standard_name": "northward_wind", "long_name": "10 metre V wind component", "units": "m s**-1", "param": "3.2.0", "institution": "DWD"}, "data": [0.46, 1.08, 1.64, 1.41, 1.26, 1.58, 1.78, 1.91, 1.94, 2.31, 2.36, 2.68, 3.0, 3.37, 4.02, 4.59, 4.5, 4.79, 5.57, 6.24, 5.86, 6.3, 6.29, 6.03, 5.78, 5.63, 5.46, 5.32, 4.83, 4.51, 4.1]}, "PET": {"dims": ["time"], "attrs": {"standard_name": "PET", "long_name": "physiological equivalent temperature", "units": "C"}, "data": ["null", 22.05, 18.82, 16.75, 15.65, 12.16, 11.59, 11.16, 11.14, 11.01, 10.85, 10.62, 10.56, 10.45, 10.11, 9.9, 10.03, 10.36, 10.63, 11.96, 14.72, 19.38, 23.41, 20.75, 18.56, 17.05, 17.5, 15.81, 13.49, 11.3, 10.82]}, "UTCI": {"dims": ["time"], "attrs": {"standard_name": "UTCI", "long_name": "Universal Thermal Climate Index", "units": "C"}, "data": ["null", 22.85, 20.79, 19.17, 18.5, 14.84, 14.02, 13.57, 13.58, 12.92, 12.86, 12.12, 11.49, 10.75, 9.23, 8.04, 8.29, 8.46, 7.8, 8.83, 12.96, 18.27, 22.14, 19.67, 16.94, 14.93, 15.7, 13.37, 9.86, 6.27, 5.37]}, "Tmrt": {"dims": ["time"], "attrs": {"standard_name": "Tmrt", "long_name": "Mean Radiant Temperature", "units": "C"}, "data": ["null", 39.95, 32.13, 26.15, 21.48, 11.93, 11.53, 11.17, 11.15, 11.86, 11.7, 11.65, 11.73, 11.78, 11.69, 12.11, 12.96, 13.72, 14.56, 19.3, 25.63, 42.14, 54.99, 49.22, 40.34, 34.13, 36.73, 32.22, 22.37, 12.78, 12.34]}, "IO": {"dims": ["time"], "attrs": {"standard_name": "IO", "long_name": "Clear-sky solar radiation", "units": "W/m/m"}, "data": ["null", 559.65, 411.18, 248.86, 82.33, 0.0, 0.0, 0.0, 0.0, 0.0, 0.0, 0.0, 0.0, 0.0, 0.0, 65.01, 231.18, 394.29, 541.82, 662.46, 747.29, 792.08, 796.71, 754.86, 671.1, 552.52, 406.67, 243.97, 77.0, 0.0, 0.0]}, "altitude": {"dims": ["time"], "attrs": {"standard_name": "altitude", "long_name": "Solar altitude", "units": "deg"}, "data": ["null", 31.69, 22.84, 13.58, 4.41, -4.6, -12.82, -19.63, -24.68, -27.45, -27.59, -25.09, -20.26, -13.61, -5.6, 3.46, 12.55, 21.8, 30.69, 38.64, 44.88, 48.48, 48.62, 45.29, 39.22, 31.37, 22.53, 13.27, 4.11, -4.97, -13.15]}, "azimuth": {"dims": ["time"], "attrs": {"standard_name": "azimuth", "long_name": "Solar azimuth", "units": "deg"}, "data": ["null", 245.03, 258.3, 270.36, 281.97, 293.73, 306.21, 319.82, 334.77, 350.9, 7.53, 23.75, 38.85, 52.6, 65.19, 77.03, 88.65, 100.66, 113.8, 128.93, 146.9, 167.82, 190.18, 211.3, 229.53, 244.87, 258.13, 270.19, 281.8, 293.59, 306.09]}}}
