{"coords": {"time": {"dims": ["time"], "attrs": {"standard_name": "time", "axis": "T", "time_zone": "UTC"}, "data": ["2020-08-07T03:00:00", "2020-08-07T04:00:00", "2020-08-07T05:00:00", "2020-08-07T06:00:00", "2020-08-07T07:00:00", "2020-08-07T08:00:00", "2020-08-07T09:00:00", "2020-08-07T10:00:00", "2020-08-07T11:00:00", "2020-08-07T12:00:00", "2020-08-07T13:00:00", "2020-08-07T14:00:00", "2020-08-07T15:00:00", "2020-08-07T16:00:00", "2020-08-07T17:00:00", "2020-08-07T18:00:00", "2020-08-07T19:00:00", "2020-08-07T20:00:00", "2020-08-07T21:00:00", "2020-08-07T22:00:00", "2020-08-07T23:00:00", "2020-08-08T00:00:00", "2020-08-08T01:00:00", "2020-08-08T02:00:00", "2020-08-08T03:00:00", "2020-08-08T04:00:00", "2020-08-08T05:00:00", "2020-08-08T06:00:00", "2020-08-08T07:00:00", "2020-08-08T08:00:00", "2020-08-08T09:00:00"]}, "lon": {"dims": [], "attrs": {"standard_name": "longitude", "long_name": "longitude", "units": "degrees_east", "axis": "X"}, "data": 22.125}, "lat": {"dims": [], "attrs": {"standard_name": "latitude", "long_name": "latitude", "units": "degrees_north", "axis": "Y"}, "data": 65.5625}, "Name": {"dims": [], "attrs": {}, "data": "Lule\u00e5"}, "Id": {"dims": [], "attrs": {}, "data": 162015}}, "attrs": {}, "dims": {"time": 31}, "data_vars": {"downward_direct": {"dims": ["time"], "attrs": {"long_name": "Downward direct short wave radiation flux at surface (mean over hour time time-stamp)", "units": "W m-2", "param": "198.4.0", "institution": "DWD"}, "data": [0.0, 13.32, 12.79, 36.19, 99.2, 76.62, 129.09, 97.73, 220.05, 162.55, 96.05, 245.78, 298.5, 208.49, 140.33, 51.27, 11.36, 0.24, 0.08, 0.0, 0.0, 0.0, 0.05, 0.0, 1.02, 15.12, 69.92, 63.97, 99.28, 187.37, 323.3]}, "downward_diffuse": {"dims": ["time"], "attrs": {"long_name": "Downward diffusive short wave radiation flux at surface (mean over hour time time-stamp)", "units": "W m-2", "param": "199.4.0", "institution": "DWD"}, "data": [0.0, 38.55, 64.62, 96.0, 157.02, 177.88, 263.82, 324.38, 258.44, 283.92, 285.29, 177.52, 95.64, 85.05, 58.02, 48.34, 20.33, 0.0, 0.0, 0.0, 0.0, 0.0, 0.0, 0.0, 12.9, 47.93, 79.16, 126.21, 165.97, 193.54, 174.41]}, "relative_humidity": {"dims": ["time"], "attrs": {"standard_name": "relative_humidity", "long_name": "2 metre relative humidity", "units": "%", "param": "1.1.0", "institution": "DWD"}, "data": [80.51, 79.89, 77.96, 74.59, 72.11, 72.98, 70.31, 70.57, 66.45, 66.53, 66.34, 77.82, 76.4, 80.15, 79.9, 81.11, 84.99, 89.42, 91.32, 93.15, 95.15, 95.87, 96.32, 97.05, 97.66, 95.04, 90.53, 88.22, 85.25, 81.74, 80.03]}, "air_temperature": {"dims": ["time"], "attrs": {"standard_name": "air_temperature", "long_name": "2 metre temperature", "units": "C", "param": "0.0.0", "institution": "DWD"}, "data": [15.28, 15.92, 16.62, 17.8, 18.95, 19.54, 20.56, 21.17, 21.69, 21.91, 22.03, 21.64, 21.18, 20.49, 19.89, 18.99, 17.73, 16.82, 16.43, 16.32, 16.16, 16.12, 16.17, 16.03, 16.15, 16.93, 17.91, 18.26, 18.52, 19.02, 19.33]}, "eastward_wind": {"dims": ["time"], "attrs": {"standard_name": "eastward_wind", "long_name": "10 metre U wind component", "units": "m s**-1", "param": "2.2.0", "institution": "DWD"}, "data": [0.65, 0.83, 0.98, 0.87, 1.41, 1.39, 1.12, 0.94, 1.49, 1.21, 0.28, -0.31, 0.0, -0.15, 0.21, -0.01, -0.36, -0.42, -0.27, -0.09, -0.07, -0.39, -0.54, -0.77, -0.56, -0.54, -0.92, -0.97, -1.13, -1.35, -1.52]}, "northward_wind": {"dims": ["time"], "attrs": {"standard_name": "northward_wind", "long_name": "10 metre V wind component", "units": "m s**-1", "param": "3.2.0", "institution": "DWD"}, "data": [0.79, 0.7, 0.77, 0.67, 0.73, 1.01, 1.05, 1.03, 0.82, 1.13, 1.91, 2.75, 2.5, 2.49, 2.08, 1.49, 1.3, 1.2, 1.16, 1.13, 0.97, 0.82, 0.68, 0.54, 0.8, 0.65, 0.55, 1.31, 1.56, 1.67, 2.17]}, "PET": {"dims": ["time"], "attrs": {"standard_name": "PET", "long_name": "physiological equivalent temperature", "units": "C"}, "data": ["null", 14.14, 14.73, 17.85, 21.52, 21.46, 26.63, 28.25, 29.4, 29.02, 27.38, 27.73, 28.8, 26.34, 25.0, 21.54, 17.5, 12.67, 12.34, 12.3, 12.35, 12.46, 12.56, 12.32, 13.15, 16.24, 19.54, 19.18, 20.61, 23.01, 25.51]}, "UTCI": {"dims": ["time"], "attrs": {"standard_name": "UTCI", "long_name": "Universal Thermal Climate Index", "units": "C"}, "data": ["null", 17.04, 17.54, 20.31, 23.32, 23.36, 26.82, 27.91, 28.54, 28.36, 27.33, 27.62, 28.28, 26.81, 26.0, 23.71, 20.43, 15.84, 15.6, 15.65, 15.81, 15.96, 16.08, 15.85, 16.71, 19.49, 22.36, 22.08, 23.1, 24.64, 26.04]}, "Tmrt": {"dims": ["time"], "attrs": {"standard_name": "Tmrt", "long_name": "Mean Radiant Temperature", "units": "C"}, "data": ["null", 17.82, 18.79, 24.45, 34.33, 33.57, 42.41, 43.95, 47.29, 45.8, 43.27, 48.49, 50.87, 46.62, 42.86, 33.51, 24.69, 11.95, 11.56, 11.46, 11.32, 11.47, 11.51, 11.38, 13.64, 19.92, 28.18, 29.69, 34.56, 40.44, 48.12]}, "IO": {"dims": ["time"], "attrs": {"standard_name": "IO", "long_name": "Clear-sky solar radiation", "units": "W/m/m"}, "data": ["null", 151.73, 258.89, 367.2, 468.79, 556.44, 624.87, 668.53, 686.79, 675.39, 636.56, 569.46, 486.37, 387.14, 280.45, 172.92, 73.04, 0.0, 0.0, 0.0, 0.0, 0.0, 0.0, 0.0, 50.05, 145.93, 252.27, 360.22, 462.18, 550.74, 619.68]}, "altitude": {"dims": ["time"], "attrs": {"standard_name": "altitude", "long_name": "Solar altitude", "units": "deg"}, "data": ["null", 8.2, 14.12, 20.28, 26.31, 31.81, 36.34, 39.42, 40.66, 39.88, 37.19, 32.94, 27.61, 21.65, 15.47, 9.44, 3.93, -0.45, -4.88, -7.45, -8.43, -7.84, -5.69, -1.46, 2.67, 7.95, 13.88, 20.04, 26.06, 31.56, 36.07]}, "azimuth": {"dims": ["time"], "attrs": {"standard_name": "azimuth", "long_name": "Solar azimuth", "units": "deg"}, "data": ["null", 68.12, 81.48, 95.1, 109.34, 124.57, 141.1, 158.94, 177.71, 196.59, 214.71, 231.55, 247.06, 261.49, 275.22, 288.6, 301.97, 315.54, 329.47, 343.75, 358.26, 12.81, 27.16, 41.19, 54.85, 68.27, 81.63, 95.26, 109.5, 124.73, 141.23]}}}
