{"coords": {"time": {"dims": ["time"], "attrs": {"standard_name": "time", "axis": "T", "time_zone": "UTC"}, "data": ["2020-07-09T09:00:00", "2020-07-09T10:00:00", "2020-07-09T11:00:00", "2020-07-09T12:00:00", "2020-07-09T13:00:00", "2020-07-09T14:00:00", "2020-07-09T15:00:00", "2020-07-09T16:00:00", "2020-07-09T17:00:00", "2020-07-09T18:00:00", "2020-07-09T19:00:00", "2020-07-09T20:00:00", "2020-07-09T21:00:00", "2020-07-09T22:00:00", "2020-07-09T23:00:00", "2020-07-10T00:00:00", "2020-07-10T01:00:00", "2020-07-10T02:00:00", "2020-07-10T03:00:00", "2020-07-10T04:00:00", "2020-07-10T05:00:00", "2020-07-10T06:00:00", "2020-07-10T07:00:00", "2020-07-10T08:00:00", "2020-07-10T09:00:00", "2020-07-10T10:00:00", "2020-07-10T11:00:00", "2020-07-10T12:00:00", "2020-07-10T13:00:00", "2020-07-10T14:00:00", "2020-07-10T15:00:00"]}, "lon": {"dims": [], "attrs": {"standard_name": "longitude", "long_name": "longitude", "units": "degrees_east", "axis": "X"}, "data": 13.1875}, "lat": {"dims": [], "attrs": {"standard_name": "latitude", "long_name": "latitude", "units": "degrees_north", "axis": "Y"}, "data": 55.6875}, "Name": {"dims": [], "attrs": {}, "data": "Lund"}, "Id": {"dims": [], "attrs": {}, "data": 53445}}, "attrs": {}, "dims": {"time": 31}, "data_vars": {"downward_direct": {"dims": ["time"], "attrs": {"long_name": "Downward direct short wave radiation flux at surface (mean over hour time time-stamp)", "units": "W m-2", "param": "198.4.0", "institution": "DWD"}, "data": [0.0, 507.69, 426.19, 306.06, 387.06, 240.66, 216.99, 104.62, 130.14, 55.98, 16.26, 0.93, 0.0, 0.09, 0.06, 0.0, 0.0, 0.0, 0.1, 2.44, 20.57, 36.33, 87.02, 47.13, 54.88, 109.27, 63.88, 18.51, 103.96, 66.28, 14.89]}, "downward_diffuse": {"dims": ["time"], "attrs": {"long_name": "Downward diffusive short wave radiation flux at surface (mean over hour time time-stamp)", "units": "W m-2", "param": "199.4.0", "institution": "DWD"}, "data": [0.0, 236.58, 317.94, 357.83, 305.93, 321.66, 281.32, 262.64, 156.73, 110.51, 55.16, 8.99, 0.0, 0.0, 0.0, 0.0, 0.0, 0.0, 0.0, 33.28, 79.96, 146.57, 205.75, 273.94, 288.89, 346.7, 306.04, 347.94, 348.63, 239.4, 157.87]}, "relative_humidity": {"dims": ["time"], "attrs": {"standard_name": "relative_humidity", "long_name": "2 metre relative humidity", "units": "%", "param": "1.1.0", "institution": "DWD"}, "data": [58.67, 54.26, 49.12, 49.82, 49.26, 51.13, 52.75, 53.95, 55.66, 59.95, 71.79, 80.29, 87.69, 92.37, 94.18, 95.37, 95.34, 95.81, 100.0, 99.37, 94.12, 86.63, 69.47, 63.32, 60.66, 58.45, 59.75, 59.54, 61.16, 62.19, 67.51]}, "air_temperature": {"dims": ["time"], "attrs": {"standard_name": "air_temperature", "long_name": "2 metre temperature", "units": "C", "param": "0.0.0", "institution": "DWD"}, "data": [15.49, 16.1, 16.82, 16.86, 17.29, 17.06, 17.0, 16.72, 16.55, 15.67, 14.35, 13.07, 12.01, 11.28, 10.8, 10.51, 10.01, 9.49, 8.93, 9.65, 11.22, 12.86, 14.83, 15.61, 15.99, 16.65, 16.45, 16.6, 16.89, 16.54, 15.63]}, "eastward_wind": {"dims": ["time"], "attrs": {"standard_name": "eastward_wind", "long_name": "10 metre U wind component", "units": "m s**-1", "param": "2.2.0", "institution": "DWD"}, "data": [2.72, 2.94, 2.76, 2.93, 2.49, 2.69, 2.0, 1.26, 1.28, 1.17, 1.0, 0.66, 0.63, 0.14, -0.11, -0.68, -0.8, -0.81, -0.93, -1.01, -0.75, -0.73, -1.28, -0.52, -1.33, -1.04, -0.71, -0.07, -0.37, 1.32, 2.57]}, "northward_wind": {"dims": ["time"], "attrs": {"standard_name": "northward_wind", "long_name": "10 metre V wind component", "units": "m s**-1", "param": "3.2.0", "institution": "DWD"}, "data": [1.25, 1.51, 1.45, 1.17, 0.53, 0.59, 0.69, 0.65, 1.1, 1.69, 1.0, 0.51, 0.82, 0.58, 0.53, 0.04, 0.21, 0.05, 0.01, -0.25, -0.18, -0.19, -0.78, -0.34, 0.04, 0.91, 1.12, 0.69, 0.72, 0.05, -1.25]}, "PET": {"dims": ["time"], "attrs": {"standard_name": "PET", "long_name": "physiological equivalent temperature", "units": "C"}, "data": ["null", 23.48, 24.72, 23.32, 26.38, 23.12, 23.74, 22.49, 20.83, 16.78, 13.97, 11.82, 7.64, 7.59, 7.2, 6.82, 6.03, 5.51, 4.75, 6.55, 10.99, 14.85, 17.62, 21.65, 19.91, 23.37, 21.03, 23.81, 25.98, 19.93, 13.88]}, "UTCI": {"dims": ["time"], "attrs": {"standard_name": "UTCI", "long_name": "Universal Thermal Climate Index", "units": "C"}, "data": ["null", 23.44, 24.25, 23.29, 25.62, 23.41, 24.13, 23.29, 22.25, 18.72, 16.66, 14.83, 10.75, 10.91, 10.56, 10.25, 9.45, 8.96, 8.23, 10.11, 14.42, 17.67, 20.0, 22.08, 21.62, 23.97, 22.42, 23.56, 25.16, 21.68, 15.11]}, "Tmrt": {"dims": ["time"], "attrs": {"standard_name": "Tmrt", "long_name": "Mean Radiant Temperature", "units": "C"}, "data": ["null", 55.21, 55.39, 52.28, 54.85, 49.21, 47.1, 40.26, 38.72, 31.37, 22.55, 15.68, 6.74, 6.04, 5.56, 5.79, 5.27, 4.74, 4.2, 8.6, 16.36, 23.12, 32.35, 33.38, 35.11, 41.93, 36.81, 37.11, 42.08, 33.98, 24.94]}, "IO": {"dims": ["time"], "attrs": {"standard_name": "IO", "long_name": "Clear-sky solar radiation", "units": "W/m/m"}, "data": ["null", 840.1, 886.92, 894.42, 863.92, 797.35, 699.38, 577.23, 438.52, 293.19, 151.24, 27.21, 0.0, 0.0, 0.0, 0.0, 0.0, 0.0, 0.0, 95.05, 230.49, 374.18, 517.22, 647.57, 756.29, 835.71, 880.77, 888.59, 857.44, 792.01, 694.53]}, "altitude": {"dims": ["time"], "attrs": {"standard_name": "altitude", "long_name": "Solar altitude", "units": "deg"}, "data": ["null", 51.58, 55.67, 56.43, 53.63, 48.04, 40.75, 32.61, 24.18, 15.89, 8.13, 1.39, -4.77, -9.19, -11.65, -12.1, -10.48, -6.91, -0.89, 5.08, 12.5, 20.6, 29.0, 37.32, 45.04, 51.45, 55.54, 56.31, 53.52, 47.95, 40.67]}, "azimuth": {"dims": ["time"], "attrs": {"standard_name": "azimuth", "long_name": "Solar azimuth", "units": "deg"}, "data": ["null", 139.9, 162.37, 187.31, 211.14, 231.36, 247.95, 261.98, 274.53, 286.38, 298.11, 310.14, 322.75, 336.05, 349.94, 4.11, 18.17, 31.74, 44.64, 56.9, 68.73, 80.48, 92.66, 105.97, 121.35, 139.93, 162.36, 187.23, 211.03, 231.22, 247.82]}}}
