{"coords": {"time": {"dims": ["time"], "attrs": {"standard_name": "time", "axis": "T", "time_zone": "UTC"}, "data": ["2020-08-03T09:00:00", "2020-08-03T10:00:00", "2020-08-03T11:00:00", "2020-08-03T12:00:00", "2020-08-03T13:00:00", "2020-08-03T14:00:00", "2020-08-03T15:00:00", "2020-08-03T16:00:00", "2020-08-03T17:00:00", "2020-08-03T18:00:00", "2020-08-03T19:00:00", "2020-08-03T20:00:00", "2020-08-03T21:00:00", "2020-08-03T22:00:00", "2020-08-03T23:00:00", "2020-08-04T00:00:00", "2020-08-04T01:00:00", "2020-08-04T02:00:00", "2020-08-04T03:00:00", "2020-08-04T04:00:00", "2020-08-04T05:00:00", "2020-08-04T06:00:00", "2020-08-04T07:00:00", "2020-08-04T08:00:00", "2020-08-04T09:00:00", "2020-08-04T10:00:00", "2020-08-04T11:00:00", "2020-08-04T12:00:00", "2020-08-04T13:00:00", "2020-08-04T14:00:00", "2020-08-04T15:00:00"]}, "lon": {"dims": [], "attrs": {"standard_name": "longitude", "long_name": "longitude", "units": "degrees_east", "axis": "X"}, "data": 16.125}, "lat": {"dims": [], "attrs": {"standard_name": "latitude", "long_name": "latitude", "units": "degrees_north", "axis": "Y"}, "data": 58.5625}, "Name": {"dims": [], "attrs": {}, "data": "Norrk\u00f6ping"}, "Id": {"dims": [], "attrs": {}, "data": 86655}}, "attrs": {}, "dims": {"time": 31}, "data_vars": {"downward_direct": {"dims": ["time"], "attrs": {"long_name": "Downward direct short wave radiation flux at surface (mean over hour time time-stamp)", "units": "W m-2", "param": "198.4.0", "institution": "DWD"}, "data": [0.0, 504.72, 507.78, 555.75, 502.88, 336.3, 288.17, 292.31, 192.34, 82.67, 10.36, 0.08, 0.02, 0.0, 0.02, 0.0, 0.09, 0.0, 0.06, 6.1, 29.64, 66.7, 162.82, 225.0, 294.88, 535.12, 599.95, 642.55, 617.07, 541.34, 434.58]}, "downward_diffuse": {"dims": ["time"], "attrs": {"long_name": "Downward diffusive short wave radiation flux at surface (mean over hour time time-stamp)", "units": "W m-2", "param": "199.4.0", "institution": "DWD"}, "data": [0.0, 176.29, 194.19, 172.34, 169.72, 186.44, 165.87, 100.82, 68.89, 47.91, 22.23, 0.0, 0.0, 0.0, 0.0, 0.0, 0.0, 0.0, 0.0, 20.76, 74.75, 134.32, 172.63, 218.64, 247.33, 156.91, 148.77, 118.6, 103.63, 96.81, 91.1]}, "relative_humidity": {"dims": ["time"], "attrs": {"standard_name": "relative_humidity", "long_name": "2 metre relative humidity", "units": "%", "param": "1.1.0", "institution": "DWD"}, "data": [59.63, 54.17, 48.42, 43.62, 43.46, 44.26, 44.49, 45.92, 47.66, 53.38, 63.78, 72.47, 77.29, 81.97, 87.16, 89.53, 91.92, 94.96, 96.38, 96.69, 90.77, 81.35, 74.53, 67.7, 62.48, 58.81, 53.81, 46.99, 45.38, 40.55, 40.68]}, "air_temperature": {"dims": ["time"], "attrs": {"standard_name": "air_temperature", "long_name": "2 metre temperature", "units": "C", "param": "0.0.0", "institution": "DWD"}, "data": [17.99, 18.86, 19.97, 20.83, 21.11, 20.82, 20.93, 20.45, 19.72, 18.52, 16.57, 15.2, 14.33, 13.8, 13.19, 12.69, 12.12, 11.51, 11.11, 11.45, 12.96, 14.49, 15.89, 17.12, 18.1, 19.13, 19.9, 20.43, 20.54, 20.66, 20.82]}, "eastward_wind": {"dims": ["time"], "attrs": {"standard_name": "eastward_wind", "long_name": "10 metre U wind component", "units": "m s**-1", "param": "2.2.0", "institution": "DWD"}, "data": [5.04, 5.27, 5.18, 4.78, 4.99, 5.02, 4.7, 4.45, 3.78, 2.91, 2.08, 1.48, 1.64, 1.83, 1.84, 1.67, 1.46, 1.36, 1.37, 1.69, 2.31, 2.93, 2.69, 2.82, 3.23, 2.99, 3.15, 3.54, 3.93, 3.56, 3.77]}, "northward_wind": {"dims": ["time"], "attrs": {"standard_name": "northward_wind", "long_name": "10 metre V wind component", "units": "m s**-1", "param": "3.2.0", "institution": "DWD"}, "data": [1.51, 1.52, 1.44, 1.72, 1.25, 1.17, 0.97, 0.67, 0.37, 0.26, 0.66, 0.94, 0.89, 0.83, 0.85, 0.85, 0.96, 1.1, 1.0, 0.89, 0.67, -0.04, 0.26, 0.33, 0.29, 0.59, 0.8, 0.91, 0.9, 0.52, 0.82]}, "PET": {"dims": ["time"], "attrs": {"standard_name": "PET", "long_name": "physiological equivalent temperature", "units": "C"}, "data": ["null", 22.72, 24.68, 26.78, 26.91, 24.4, 24.55, 24.67, 23.02, 20.12, 14.94, 10.34, 9.35, 8.72, 8.08, 7.69, 7.19, 6.55, 6.17, 7.84, 10.75, 13.61, 17.63, 20.39, 22.8, 27.35, 28.62, 28.87, 28.47, 28.99, 27.85]}, "UTCI": {"dims": ["time"], "attrs": {"standard_name": "UTCI", "long_name": "Universal Thermal Climate Index", "units": "C"}, "data": ["null", 21.62, 22.99, 24.54, 24.62, 22.75, 23.02, 23.3, 22.53, 20.99, 16.75, 12.37, 11.33, 10.58, 10.02, 9.89, 9.61, 9.0, 8.71, 10.51, 13.07, 15.35, 19.55, 21.83, 23.19, 26.26, 26.87, 26.68, 26.2, 26.67, 25.78]}, "Tmrt": {"dims": ["time"], "attrs": {"standard_name": "Tmrt", "long_name": "Mean Radiant Temperature", "units": "C"}, "data": ["null", 54.78, 56.24, 58.16, 57.87, 52.17, 51.05, 51.78, 46.91, 38.59, 23.66, 10.07, 9.22, 8.73, 8.14, 7.75, 7.19, 6.58, 6.18, 11.89, 19.72, 27.47, 36.25, 42.48, 48.03, 55.34, 57.48, 58.79, 59.16, 58.37, 56.33]}, "IO": {"dims": ["time"], "attrs": {"standard_name": "IO", "long_name": "Clear-sky solar radiation", "units": "W/m/m"}, "data": ["null", 761.89, 799.81, 802.0, 766.47, 697.61, 599.56, 479.47, 345.5, 206.54, 74.26, 0.0, 0.0, 0.0, 0.0, 0.0, 0.0, 0.0, 0.0, 65.95, 196.13, 333.67, 467.11, 587.51, 686.35, 756.19, 793.94, 797.5, 762.94, 696.25, 597.7]}, "altitude": {"dims": ["time"], "attrs": {"standard_name": "altitude", "long_name": "Solar altitude", "units": "deg"}, "data": ["null", 45.47, 48.36, 48.43, 45.67, 40.62, 34.04, 26.59, 18.81, 11.11, 3.94, -2.14, -8.17, -12.0, -14.04, -14.1, -12.19, -8.47, -2.67, 3.5, 10.61, 18.27, 26.04, 33.49, 40.11, 45.22, 48.1, 48.16, 45.4, 40.37, 33.79]}, "azimuth": {"dims": ["time"], "attrs": {"standard_name": "azimuth", "long_name": "Solar azimuth", "units": "deg"}, "data": ["null", 148.0, 168.59, 190.22, 210.9, 229.32, 245.35, 259.54, 272.58, 285.07, 297.51, 310.29, 323.65, 337.67, 352.22, 6.99, 21.57, 35.63, 49.04, 61.86, 74.33, 86.83, 99.84, 113.96, 129.88, 148.14, 168.67, 190.22, 210.83, 229.2, 245.21]}}}
