{"coords": {"time": {"dims": ["time"], "attrs": {"standard_name": "time", "axis": "T", "time_zone": "UTC"}, "data": ["2020-07-13T15:00:00", "2020-07-13T16:00:00", "2020-07-13T17:00:00", "2020-07-13T18:00:00", "2020-07-13T19:00:00", "2020-07-13T20:00:00", "2020-07-13T21:00:00", "2020-07-13T22:00:00", "2020-07-13T23:00:00", "2020-07-14T00:00:00", "2020-07-14T01:00:00", "2020-07-14T02:00:00", "2020-07-14T03:00:00", "2020-07-14T04:00:00", "2020-07-14T05:00:00", "2020-07-14T06:00:00", "2020-07-14T07:00:00", "2020-07-14T08:00:00", "2020-07-14T09:00:00", "2020-07-14T10:00:00", "2020-07-14T11:00:00", "2020-07-14T12:00:00", "2020-07-14T13:00:00", "2020-07-14T14:00:00", "2020-07-14T15:00:00", "2020-07-14T16:00:00", "2020-07-14T17:00:00", "2020-07-14T18:00:00", "2020-07-14T19:00:00", "2020-07-14T20:00:00", "2020-07-14T21:00:00"]}, "lon": {"dims": [], "attrs": {"standard_name": "longitude", "long_name": "longitude", "units": "degrees_east", "axis": "X"}, "data": 19.5}, "lat": {"dims": [], "attrs": {"standard_name": "latitude", "long_name": "latitude", "units": "degrees_north", "axis": "Y"}, "data": 59.4375}, "Name": {"dims": [], "attrs": {}, "data": "Svenska H\u00f6garna"}, "Id": {"dims": [], "attrs": {}, "data": 99275}}, "attrs": {}, "dims": {"time": 31}, "data_vars": {"downward_direct": {"dims": ["time"], "attrs": {"long_name": "Downward direct short wave radiation flux at surface (mean over hour time time-stamp)", "units": "W m-2", "param": "198.4.0", "institution": "DWD"}, "data": [0.0, 315.45, 201.67, 99.56, 26.31, 1.22, 0.0, 0.02, 0.0, 0.02, 0.02, 0.01, 1.01, 6.57, 1.19, 3.93, 110.5, 202.39, 234.5, 366.76, 406.01, 474.29, 410.67, 205.22, 131.47, 32.68, 52.26, 27.52, 7.59, 0.87, 0.0]}, "downward_diffuse": {"dims": ["time"], "attrs": {"long_name": "Downward diffusive short wave radiation flux at surface (mean over hour time time-stamp)", "units": "W m-2", "param": "199.4.0", "institution": "DWD"}, "data": [0.0, 92.46, 79.29, 59.93, 35.26, 6.07, 0.0, 0.0, 0.0, 0.0, 0.0, 0.0, 15.51, 47.22, 67.24, 106.99, 180.12, 227.69, 263.32, 253.51, 271.16, 231.73, 237.21, 279.0, 227.3, 173.61, 126.73, 80.94, 37.77, 5.14, 0.0]}, "relative_humidity": {"dims": ["time"], "attrs": {"standard_name": "relative_humidity", "long_name": "2 metre relative humidity", "units": "%", "param": "1.1.0", "institution": "DWD"}, "data": [77.95, 74.61, 71.31, 70.08, 69.59, 72.64, 75.25, 76.05, 74.31, 75.36, 81.12, 85.79, 88.79, 89.88, 89.66, 88.75, 88.64, 89.22, 89.78, 90.54, 89.94, 87.85, 85.24, 83.69, 83.36, 83.96, 84.43, 84.92, 84.59, 84.11, 84.19]}, "air_temperature": {"dims": ["time"], "attrs": {"standard_name": "air_temperature", "long_name": "2 metre temperature", "units": "C", "param": "0.0.0", "institution": "DWD"}, "data": [14.17, 14.18, 14.3, 14.33, 14.36, 14.25, 14.16, 14.16, 14.27, 14.37, 14.41, 14.41, 14.43, 14.48, 14.58, 14.68, 14.75, 14.76, 14.79, 14.79, 14.79, 14.77, 14.81, 14.82, 14.82, 14.8, 14.78, 14.77, 14.76, 14.74, 14.7]}, "eastward_wind": {"dims": ["time"], "attrs": {"standard_name": "eastward_wind", "long_name": "10 metre U wind component", "units": "m s**-1", "param": "2.2.0", "institution": "DWD"}, "data": [-0.58, -0.17, -0.48, -0.8, -0.34, 0.7, 1.18, 1.44, 1.63, 1.63, 2.27, 2.01, 1.79, 1.45, 1.09, 0.89, 0.52, 0.59, 0.49, 0.89, 1.52, 1.77, 1.23, 1.14, 0.68, 0.35, 0.22, 0.77, 0.87, 0.97, 1.08]}, "northward_wind": {"dims": ["time"], "attrs": {"standard_name": "northward_wind", "long_name": "10 metre V wind component", "units": "m s**-1", "param": "3.2.0", "institution": "DWD"}, "data": [-3.83, -4.19, -2.62, -1.49, 0.43, 1.89, 2.9, 3.55, 3.94, 4.43, 4.51, 4.37, 3.71, 3.21, 2.95, 2.86, 3.16, 3.62, 4.2, 5.12, 5.56, 5.05, 4.7, 4.54, 3.95, 3.83, 3.38, 3.38, 3.11, 3.06, 2.89]}, "PET": {"dims": ["time"], "attrs": {"standard_name": "PET", "long_name": "physiological equivalent temperature", "units": "C"}, "data": ["null", 17.72, 18.67, 18.4, 17.76, 11.82, 8.45, 8.21, 8.18, 8.32, 8.32, 8.41, 9.05, 10.04, 10.41, 11.43, 15.01, 16.36, 16.76, 17.46, 17.63, 18.6, 18.83, 16.64, 15.87, 13.09, 13.8, 12.62, 11.49, 11.07, 9.12]}, "UTCI": {"dims": ["time"], "attrs": {"standard_name": "UTCI", "long_name": "Universal Thermal Climate Index", "units": "C"}, "data": ["null", 18.5, 20.59, 20.71, 19.27, 14.02, 8.15, 6.62, 5.8, 5.31, 4.98, 5.6, 7.76, 10.19, 11.23, 12.76, 16.87, 17.94, 17.88, 17.93, 17.76, 19.01, 19.47, 17.15, 16.85, 13.66, 15.1, 13.56, 12.36, 11.84, 9.29]}, "Tmrt": {"dims": ["time"], "attrs": {"standard_name": "Tmrt", "long_name": "Mean Radiant Temperature", "units": "C"}, "data": ["null", 47.95, 43.35, 36.69, 26.02, 18.67, 8.8, 8.82, 8.9, 9.75, 9.83, 9.87, 11.87, 15.03, 15.43, 18.77, 32.58, 39.14, 42.63, 48.82, 51.49, 53.65, 52.44, 43.94, 38.57, 27.48, 28.81, 24.58, 19.46, 17.82, 9.48]}, "IO": {"dims": ["time"], "attrs": {"standard_name": "IO", "long_name": "Clear-sky solar radiation", "units": "W/m/m"}, "data": ["null", 507.43, 379.55, 248.74, 124.88, 20.4, 0.0, 0.0, 0.0, 0.0, 0.0, 0.0, 57.91, 170.93, 297.56, 427.44, 551.19, 660.24, 747.12, 805.94, 833.12, 826.95, 787.33, 716.53, 619.4, 502.77, 374.93, 244.72, 121.68, 18.11, 0.0]}, "altitude": {"dims": ["time"], "attrs": {"standard_name": "altitude", "long_name": "Solar altitude", "units": "deg"}, "data": ["null", 28.43, 20.83, 13.46, 6.69, 1.02, -3.97, -7.43, -8.92, -8.55, -6.33, -1.71, 3.08, 9.28, 16.33, 23.82, 31.4, 38.63, 44.97, 49.69, 52.01, 51.4, 48.01, 42.53, 35.75, 28.32, 20.71, 13.34, 6.57, 0.9, -4.14]}, "azimuth": {"dims": ["time"], "attrs": {"standard_name": "azimuth", "long_name": "Solar azimuth", "units": "deg"}, "data": ["null", 264.87, 277.72, 290.09, 302.43, 315.06, 328.18, 341.8, 355.8, 9.89, 23.77, 37.2, 50.12, 62.61, 74.92, 87.43, 100.65, 115.24, 131.94, 151.36, 173.22, 195.79, 216.78, 235.06, 250.81, 264.75, 277.61, 289.99, 302.33, 314.98, 328.11]}}}
