{"coords": {"time": {"dims": ["time"], "attrs": {"standard_name": "time", "axis": "T", "time_zone": "UTC"}, "data": ["2020-06-21T15:00:00", "2020-06-21T16:00:00", "2020-06-21T17:00:00", "2020-06-21T18:00:00", "2020-06-21T19:00:00", "2020-06-21T20:00:00", "2020-06-21T21:00:00", "2020-06-21T22:00:00", "2020-06-21T23:00:00", "2020-06-22T00:00:00", "2020-06-22T01:00:00", "2020-06-22T02:00:00", "2020-06-22T03:00:00", "2020-06-22T04:00:00", "2020-06-22T05:00:00", "2020-06-22T06:00:00", "2020-06-22T07:00:00", "2020-06-22T08:00:00", "2020-06-22T09:00:00", "2020-06-22T10:00:00", "2020-06-22T11:00:00", "2020-06-22T12:00:00", "2020-06-22T13:00:00", "2020-06-22T14:00:00", "2020-06-22T15:00:00", "2020-06-22T16:00:00", "2020-06-22T17:00:00", "2020-06-22T18:00:00", "2020-06-22T19:00:00", "2020-06-22T20:00:00", "2020-06-22T21:00:00"]}, "lon": {"dims": [], "attrs": {"standard_name": "longitude", "long_name": "longitude", "units": "degrees_east", "axis": "X"}, "data": 18.625}, "lat": {"dims": [], "attrs": {"standard_name": "latitude", "long_name": "latitude", "units": "degrees_north", "axis": "Y"}, "data": 67.9375}, "Name": {"dims": [], "attrs": {}, "data": "Tarfala"}, "Id": {"dims": [], "attrs": {}, "data": 178985}}, "attrs": {}, "dims": {"time": 31}, "data_vars": {"downward_direct": {"dims": ["time"], "attrs": {"long_name": "Downward direct short wave radiation flux at surface (mean over hour time time-stamp)", "units": "W m-2", "param": "198.4.0", "institution": "DWD"}, "data": [0.0, 413.41, 314.47, 216.89, 131.92, 67.57, 27.29, 8.83, 5.0, 5.65, 4.05, 10.88, 53.96, 150.27, 252.08, 347.44, 450.4, 538.57, 608.01, 649.69, 644.0, 597.14, 604.69, 558.8, 468.52, 361.1, 210.23, 96.07, 51.65, 16.07, 5.21]}, "downward_diffuse": {"dims": ["time"], "attrs": {"long_name": "Downward diffusive short wave radiation flux at surface (mean over hour time time-stamp)", "units": "W m-2", "param": "199.4.0", "institution": "DWD"}, "data": [0.0, 61.88, 56.69, 50.68, 43.38, 34.13, 23.24, 13.55, 8.1, 10.12, 24.66, 47.51, 62.77, 57.55, 57.35, 64.58, 65.7, 68.78, 71.84, 76.96, 96.41, 121.92, 95.64, 80.83, 86.01, 90.23, 107.33, 112.2, 75.33, 50.71, 28.04]}, "relative_humidity": {"dims": ["time"], "attrs": {"standard_name": "relative_humidity", "long_name": "2 metre relative humidity", "units": "%", "param": "1.1.0", "institution": "DWD"}, "data": [34.85, 35.97, 38.49, 44.48, 50.03, 50.63, 53.8, 53.7, 50.18, 45.84, 43.05, 43.62, 44.48, 44.31, 42.58, 41.0, 38.37, 35.63, 34.34, 36.92, 36.89, 36.19, 33.08, 31.91, 31.08, 36.37, 37.76, 45.01, 45.9, 48.77, 53.23]}, "air_temperature": {"dims": ["time"], "attrs": {"standard_name": "air_temperature", "long_name": "2 metre temperature", "units": "C", "param": "0.0.0", "institution": "DWD"}, "data": [18.51, 18.24, 17.85, 17.26, 16.56, 15.64, 14.23, 13.02, 12.14, 11.69, 11.73, 12.2, 13.11, 14.47, 15.69, 16.66, 17.63, 18.45, 19.15, 19.58, 19.9, 20.11, 20.21, 20.18, 19.93, 19.3, 18.73, 17.9, 17.24, 16.65, 15.71]}, "eastward_wind": {"dims": ["time"], "attrs": {"standard_name": "eastward_wind", "long_name": "10 metre U wind component", "units": "m s**-1", "param": "2.2.0", "institution": "DWD"}, "data": [3.71, 3.4, 2.93, 3.0, 2.27, 1.93, 2.06, 2.25, 2.39, 2.57, 2.66, 2.54, 2.39, 1.97, 1.74, 1.73, 1.79, 2.01, 2.05, 2.48, 2.74, 2.99, 2.05, 1.56, 0.75, 1.07, 1.05, 0.81, 0.66, 0.34, 0.58]}, "northward_wind": {"dims": ["time"], "attrs": {"standard_name": "northward_wind", "long_name": "10 metre V wind component", "units": "m s**-1", "param": "3.2.0", "institution": "DWD"}, "data": [-0.77, -1.04, -1.17, -0.74, -0.29, 0.15, 0.16, -0.02, -0.07, -0.14, -0.08, -0.04, -0.22, -0.33, -0.07, -0.08, -0.21, -0.72, -1.62, -2.73, -3.4, -3.79, -4.55, -4.82, -4.62, -4.49, -4.1, -3.14, -2.21, -0.82, -0.79]}, "PET": {"dims": ["time"], "attrs": {"standard_name": "PET", "long_name": "physiological equivalent temperature", "units": "C"}, "data": ["null", 24.71, 23.86, 21.63, 20.53, 18.27, 14.44, 10.94, 9.34, 7.64, 7.0, 8.32, 11.86, 17.42, 21.81, 24.81, 27.38, 28.45, 28.76, 27.41, 26.67, 26.16, 26.29, 25.92, 25.42, 23.47, 20.8, 18.3, 17.01, 16.76, 14.21]}, "UTCI": {"dims": ["time"], "attrs": {"standard_name": "UTCI", "long_name": "Universal Thermal Climate Index", "units": "C"}, "data": ["null", 23.74, 23.41, 21.99, 21.76, 19.93, 16.33, 12.47, 10.45, 8.0, 6.88, 8.73, 13.13, 19.07, 22.67, 24.61, 26.18, 26.8, 26.87, 25.51, 24.65, 24.06, 24.06, 23.74, 23.54, 22.19, 20.27, 18.67, 18.19, 18.37, 16.28]}, "Tmrt": {"dims": ["time"], "attrs": {"standard_name": "Tmrt", "long_name": "Mean Radiant Temperature", "units": "C"}, "data": ["null", 54.37, 51.33, 47.07, 41.74, 35.33, 27.83, 20.28, 17.71, 13.4, 10.94, 14.3, 23.95, 35.96, 43.24, 47.8, 51.87, 54.78, 56.81, 57.89, 58.13, 58.01, 58.77, 58.18, 56.27, 52.8, 45.63, 35.68, 29.52, 23.0, 18.43]}, "IO": {"dims": ["time"], "attrs": {"standard_name": "IO", "long_name": "Clear-sky solar radiation", "units": "W/m/m"}, "data": ["null", 522.3, 426.86, 329.2, 237.17, 157.31, 94.21, 52.61, 34.36, 39.29, 67.71, 119.21, 190.45, 276.15, 370.56, 467.03, 559.24, 640.88, 705.58, 747.38, 766.92, 761.83, 733.51, 681.26, 609.7, 521.35, 426.62, 328.87, 237.62, 157.27, 93.98]}, "altitude": {"dims": ["time"], "attrs": {"standard_name": "altitude", "long_name": "Solar altitude", "units": "deg"}, "data": ["null", 28.9, 23.29, 17.81, 12.75, 8.39, 4.99, 2.74, 1.75, 2.01, 3.52, 6.27, 10.1, 14.78, 20.05, 25.63, 31.19, 36.38, 40.78, 43.93, 45.42, 45.03, 42.81, 39.08, 34.3, 28.91, 23.3, 17.82, 12.76, 8.4, 4.99]}, "azimuth": {"dims": ["time"], "attrs": {"standard_name": "azimuth", "long_name": "Solar azimuth", "units": "deg"}, "data": ["null", 261.3, 275.29, 288.76, 302.02, 315.28, 328.68, 342.26, 355.99, 9.74, 23.42, 36.93, 50.26, 63.49, 76.81, 90.46, 104.77, 120.12, 136.82, 154.97, 174.24, 193.81, 212.69, 230.26, 246.37, 261.24, 275.24, 288.71, 301.97, 315.23, 328.63]}}}
