{"coords": {"time": {"dims": ["time"], "attrs": {"standard_name": "time", "axis": "T", "time_zone": "UTC"}, "data": ["2020-08-04T09:00:00", "2020-08-04T10:00:00", "2020-08-04T11:00:00", "2020-08-04T12:00:00", "2020-08-04T13:00:00", "2020-08-04T14:00:00", "2020-08-04T15:00:00", "2020-08-04T16:00:00", "2020-08-04T17:00:00", "2020-08-04T18:00:00", "2020-08-04T19:00:00", "2020-08-04T20:00:00", "2020-08-04T21:00:00", "2020-08-04T22:00:00", "2020-08-04T23:00:00", "2020-08-05T00:00:00", "2020-08-05T01:00:00", "2020-08-05T02:00:00", "2020-08-05T03:00:00", "2020-08-05T04:00:00", "2020-08-05T05:00:00", "2020-08-05T06:00:00", "2020-08-05T07:00:00", "2020-08-05T08:00:00", "2020-08-05T09:00:00", "2020-08-05T10:00:00", "2020-08-05T11:00:00", "2020-08-05T12:00:00", "2020-08-05T13:00:00", "2020-08-05T14:00:00", "2020-08-05T15:00:00"]}, "lon": {"dims": [], "attrs": {"standard_name": "longitude", "long_name": "longitude", "units": "degrees_east", "axis": "X"}, "data": 18.625}, "lat": {"dims": [], "attrs": {"standard_name": "latitude", "long_name": "latitude", "units": "degrees_north", "axis": "Y"}, "data": 67.9375}, "Name": {"dims": [], "attrs": {}, "data": "Tarfala"}, "Id": {"dims": [], "attrs": {}, "data": 178985}}, "attrs": {}, "dims": {"time": 31}, "data_vars": {"downward_direct": {"dims": ["time"], "attrs": {"long_name": "Downward direct short wave radiation flux at surface (mean over hour time time-stamp)", "units": "W m-2", "param": "198.4.0", "institution": "DWD"}, "data": [0.0, 20.34, 69.84, 90.52, 72.86, 74.33, 50.86, 33.38, 21.12, 5.5, 1.88, 0.41, 0.0, 0.0, 0.02, 0.09, 0.0, 0.07, 2.32, 7.86, 9.84, 47.34, 79.21, 91.58, 121.59, 143.33, 172.44, 147.99, 19.72, 21.88, 50.43]}, "downward_diffuse": {"dims": ["time"], "attrs": {"long_name": "Downward diffusive short wave radiation flux at surface (mean over hour time time-stamp)", "units": "W m-2", "param": "199.4.0", "institution": "DWD"}, "data": [0.0, 272.87, 217.66, 201.64, 203.18, 177.57, 143.77, 96.8, 68.27, 36.99, 15.74, 3.95, 0.0, 0.0, 0.0, 0.0, 0.0, 0.38, 10.92, 31.96, 56.72, 109.58, 157.26, 167.61, 173.1, 188.53, 185.85, 216.93, 215.34, 165.07, 150.92]}, "relative_humidity": {"dims": ["time"], "attrs": {"standard_name": "relative_humidity", "long_name": "2 metre relative humidity", "units": "%", "param": "1.1.0", "institution": "DWD"}, "data": [74.56, 73.42, 73.47, 75.71, 74.05, 75.41, 77.09, 79.0, 79.85, 79.45, 81.88, 85.5, 89.48, 92.5, 93.34, 93.61, 93.33, 92.77, 92.73, 92.18, 91.18, 87.36, 80.04, 77.98, 77.81, 78.08, 73.52, 69.91, 72.5, 72.26, 72.65]}, "air_temperature": {"dims": ["time"], "attrs": {"standard_name": "air_temperature", "long_name": "2 metre temperature", "units": "C", "param": "0.0.0", "institution": "DWD"}, "data": [10.33, 10.5, 10.44, 10.29, 10.15, 9.86, 9.47, 9.13, 8.73, 8.26, 7.79, 7.44, 7.18, 6.91, 6.66, 6.41, 6.16, 6.01, 5.85, 5.93, 6.14, 6.72, 7.63, 8.06, 8.37, 8.61, 8.97, 9.45, 9.1, 8.82, 8.82]}, "eastward_wind": {"dims": ["time"], "attrs": {"standard_name": "eastward_wind", "long_name": "10 metre U wind component", "units": "m s**-1", "param": "2.2.0", "institution": "DWD"}, "data": [-0.93, -1.03, -0.96, -0.1, 0.14, -0.02, -0.3, -0.51, -0.83, -0.3, -0.29, 0.05, 0.63, 0.76, 0.55, 0.81, 0.69, 0.85, 0.89, 1.09, 1.23, 0.9, 0.37, -0.08, 0.68, 1.05, 0.6, -0.12, -0.68, -0.38, -0.02]}, "northward_wind": {"dims": ["time"], "attrs": {"standard_name": "northward_wind", "long_name": "10 metre V wind component", "units": "m s**-1", "param": "3.2.0", "institution": "DWD"}, "data": [1.27, 1.45, 1.85, 1.83, 1.9, 1.96, 1.58, 1.16, 0.99, 0.16, -0.14, -0.5, -0.8, -0.97, -1.06, -0.91, -0.93, -0.72, -0.57, -0.43, -0.52, -0.69, -0.2, 0.12, 0.6, 0.08, -0.1, -0.23, -0.28, 0.1, -0.12]}, "PET": {"dims": ["time"], "attrs": {"standard_name": "PET", "long_name": "physiological equivalent temperature", "units": "C"}, "data": ["null", 11.88, 11.37, 11.94, 11.36, 10.68, 9.78, 8.73, 7.36, 7.86, 6.69, 5.39, 2.78, 2.23, 2.01, 1.73, 1.53, 1.33, 2.17, 2.82, 3.24, 7.0, 13.02, 16.45, 11.95, 12.61, 15.73, 19.05, 12.06, 12.18, 15.53]}, "UTCI": {"dims": ["time"], "attrs": {"standard_name": "UTCI", "long_name": "Universal Thermal Climate Index", "units": "C"}, "data": ["null", 14.9, 14.14, 15.01, 14.33, 13.63, 13.0, 12.09, 10.67, 10.64, 9.59, 8.71, 5.99, 5.23, 5.07, 4.75, 4.62, 4.45, 5.56, 6.22, 6.55, 10.76, 15.18, 16.38, 15.17, 15.89, 17.75, 18.82, 14.93, 14.31, 15.61]}, "Tmrt": {"dims": ["time"], "attrs": {"standard_name": "Tmrt", "long_name": "Mean Radiant Temperature", "units": "C"}, "data": ["null", 27.21, 27.51, 28.14, 27.16, 26.08, 22.21, 17.8, 14.72, 10.01, 7.74, 6.58, 2.61, 2.35, 2.1, 1.85, 1.6, 1.13, 3.96, 6.42, 8.13, 17.05, 23.39, 24.87, 25.23, 27.82, 29.97, 30.78, 22.71, 19.64, 22.01]}, "IO": {"dims": ["time"], "attrs": {"standard_name": "IO", "long_name": "Clear-sky solar radiation", "units": "W/m/m"}, "data": ["null", 655.3, 677.69, 673.4, 644.22, 590.47, 516.5, 427.23, 329.06, 228.69, 132.96, 50.23, 0.0, 0.0, 0.0, 0.0, 0.0, 2.44, 70.4, 157.37, 254.95, 355.53, 452.2, 537.64, 605.99, 652.74, 675.79, 672.19, 641.95, 588.29, 513.78]}, "altitude": {"dims": ["time"], "attrs": {"standard_name": "altitude", "long_name": "Solar altitude", "units": "deg"}, "data": ["null", 37.5, 39.02, 38.75, 36.74, 33.25, 28.65, 23.37, 17.77, 12.23, 7.05, 2.61, -0.62, -3.62, -4.98, -4.85, -2.88, 0.11, 3.7, 8.36, 13.65, 19.23, 24.75, 29.86, 34.16, 37.24, 38.75, 38.48, 36.47, 32.98, 28.39]}, "azimuth": {"dims": ["time"], "attrs": {"standard_name": "azimuth", "long_name": "Solar azimuth", "units": "deg"}, "data": ["null", 155.18, 173.36, 191.81, 209.79, 226.79, 242.64, 257.49, 271.6, 285.29, 298.84, 312.48, 326.36, 340.49, 354.83, 9.24, 23.54, 37.61, 51.42, 65.03, 78.61, 92.4, 106.7, 121.81, 137.98, 155.27, 173.41, 191.81, 209.75, 226.72, 242.56]}}}
